xtsjspider/__init__.py
xtsjspider/__main__.py
xtsjspider/runspider.py
xtsjspider/abnormal/__init__.py
xtsjspider/abnormal/abnorm.py
xtsjspider/abnormal/cds.py
xtsjspider/db/__init__.py
xtsjspider/db/open_json.py
xtsjspider/dispatcher/__init__.py
xtsjspider/dispatcher/starte.py
xtsjspider/downloader/HTTP.py
xtsjspider/downloader/__init__.py
xtsjspider/model/__init__.py
xtsjspider/model/modeler.py
xtsjspider/parsers/__init__.py
xtsjspider/parsers/pare.py
xtsjspider-3.6.2.dist-info/METADATA
xtsjspider-3.6.2.dist-info/WHEEL
xtsjspider-3.6.2.dist-info/top_level.txt
xtsjspider-3.6.2.dist-info/RECORD
